ibis/__init__.py
ibis/ibis_protocol.py
ibis/ibis_serial.py
ibis/ibis_tcp.py
ibis/metadata.py
ibis/mono_protocol.py
ibis/mono_serial.py
pyIBIS-2.4.1.dist-info/METADATA
pyIBIS-2.4.1.dist-info/WHEEL
pyIBIS-2.4.1.dist-info/top_level.txt
pyIBIS-2.4.1.dist-info/RECORD
