Metadata-Version: 2.1
Name: pyIBIS
Version: 2.4.1
Summary: A library for sending and receiving IBIS (VDV 300) and MONO telegrams
Home-page: https://github.com/Mezgrman/pyIBISv2
Author: Julian Metzler
Author-email: git@mezgr.de
License: GPLv3
Keywords: led sign message board effect library wrapper serial text display ibis vdv300 bus next stop train mono lawo
Platform: UNKNOWN
Requires-Dist: pyserial
